{
  "version": "7",
  "dialect": "postgresql",
  "entries": [
    {
      "idx": 0,
      "version": "7",
      "when": 1776193320063,
      "tag": "20260414190200_initial_schema",
      "breakpoints": true
    },
    {
      "idx": 1,
      "version": "7",
      "when": 1776196988820,
      "tag": "20260414200308_billing_preparation",
      "breakpoints": true
    },
    {
      "idx": 2,
      "version": "7",
      "when": 1776283592739,
      "tag": "20260415200632_password_reset_flow",
      "breakpoints": true
    },
    {
      "idx": 3,
      "version": "7",
      "when": 1776284421923,
      "tag": "20260415202021_remove_interface_language",
      "breakpoints": true
    }
  ]
}